{
    "CarAgent": {
        "checkpoints": [
            {
                "steps": 48499391,
                "file_path": "results\\Brakes1Hyper2\\CarAgent\\CarAgent-48499391.onnx",
                "reward": 139.04143218994142,
                "creation_time": 1619730956.8021626
            },
            {
                "steps": 48999930,
                "file_path": "results\\Brakes1Hyper2\\CarAgent\\CarAgent-48999930.onnx",
                "reward": 139.13961791992188,
                "creation_time": 1619731380.8615932
            },
            {
                "steps": 49499124,
                "file_path": "results\\Brakes1Hyper2\\CarAgent\\CarAgent-49499124.onnx",
                "reward": null,
                "creation_time": 1619731800.1077912
            },
            {
                "steps": 49999141,
                "file_path": "results\\Brakes1Hyper2\\CarAgent\\CarAgent-49999141.onnx",
                "reward": 138.2933006286621,
                "creation_time": 1619732218.4589636
            },
            {
                "steps": 50000141,
                "file_path": "results\\Brakes1Hyper2\\CarAgent\\CarAgent-50000141.onnx",
                "reward": 138.2933006286621,
                "creation_time": 1619732218.6005573
            }
        ],
        "final_checkpoint": {
            "steps": 50000141,
            "file_path": "results\\Brakes1Hyper2\\CarAgent.onnx",
            "reward": 138.2933006286621,
            "creation_time": 1619732218.6005573
        }
    },
    "metadata": {
        "stats_format_version": "0.2.0",
        "mlagents_version": "0.24.0",
        "torch_version": "1.7.1+cu110"
    }
}