[
  {
    "epNo": 0,
    "timesteps": 0,
    "time": 0.0,
    "wallHit": 0,
    "collidedWith": "",
    "distanceCovered": 0.0,
    "maxSpeed": 0.0,
    "avgSpeed": 0.0,
    "totalReward": 0.0,
    "rewardFromCheckpoints": 0.0,
    "rewardFromFinish": 0.0,
    "rewardFromTimeRunOut": 0.0,
    "rewardFromWall": 0.0,
    "rewardFromSpeed": 0.0,
    "rewardFromTime": 0.0,
    "rewardFromBrakes": 0.0
  },
  {
    "epNo": 1,
    "timesteps": 1961,
    "time": 39.2131538,
    "wallHit": 1,
    "collidedWith": "Wall",
    "distanceCovered": 230.67030334472656,
    "maxSpeed": 9.8504104614257813,
    "avgSpeed": 5.9032028748328695,
    "totalReward": 19.9879284,
    "rewardFromCheckpoints": 56.25,
    "rewardFromFinish": 0.0,
    "rewardFromTimeRunOut": 0.0,
    "rewardFromWall": -13.0,
    "rewardFromSpeed": -4.500008,
    "rewardFromTime": -1.96203566,
    "rewardFromBrakes": -16.8000278
  },
  {
    "epNo": 2,
    "timesteps": 1831,
    "time": 36.6032028,
    "wallHit": 1,
    "collidedWith": "Wall",
    "distanceCovered": 272.35662841796875,
    "maxSpeed": 11.055172920227051,
    "avgSpeed": 7.4627909449517631,
    "totalReward": 46.17797,
    "rewardFromCheckpoints": 62.5,
    "rewardFromFinish": 0.0,
    "rewardFromTimeRunOut": 0.0,
    "rewardFromWall": -13.0,
    "rewardFromSpeed": -1.48999894,
    "rewardFromTime": -1.83202958,
    "rewardFromBrakes": 0.0
  },
  {
    "epNo": 3,
    "timesteps": 3044,
    "time": 60.8718948,
    "wallHit": 0,
    "collidedWith": "",
    "distanceCovered": 424.84222412109375,
    "maxSpeed": 10.613500595092773,
    "avgSpeed": 6.99587185951574,
    "totalReward": 138.985046,
    "rewardFromCheckpoints": 93.75,
    "rewardFromFinish": 50.0,
    "rewardFromTimeRunOut": 0.0,
    "rewardFromWall": 0.0,
    "rewardFromSpeed": -1.71999872,
    "rewardFromTime": -3.04496169,
    "rewardFromBrakes": 0.0
  },
  {
    "epNo": 4,
    "timesteps": 3024,
    "time": 60.50538,
    "wallHit": 0,
    "collidedWith": "",
    "distanceCovered": 421.23016357421875,
    "maxSpeed": 11.040749549865723,
    "avgSpeed": 6.9820441230786621,
    "totalReward": 138.205032,
    "rewardFromCheckpoints": 93.75,
    "rewardFromFinish": 50.0,
    "rewardFromTimeRunOut": 0.0,
    "rewardFromWall": 0.0,
    "rewardFromSpeed": -2.519998,
    "rewardFromTime": -3.02496314,
    "rewardFromBrakes": 0.0
  }
]