[
  {
    "epNo": 0,
    "timesteps": 0,
    "time": 0.0,
    "wallHit": 0,
    "collidedWith": "",
    "distanceCovered": 0.0,
    "maxSpeed": 0.0,
    "avgSpeed": 0.0,
    "totalReward": 0.0,
    "rewardFromCheckpoints": 0.0,
    "rewardFromFinish": 0.0,
    "rewardFromTimeRunOut": 0.0,
    "rewardFromWall": 0.0,
    "rewardFromSpeed": 0.0,
    "rewardFromTime": 0.0,
    "rewardFromBrakes": 0.0
  },
  {
    "epNo": 1,
    "timesteps": 2726,
    "time": 54.48947,
    "wallHit": 1,
    "collidedWith": "Wall",
    "distanceCovered": 408.84225463867188,
    "maxSpeed": 10.317084312438965,
    "avgSpeed": 7.5174780227653875,
    "totalReward": 73.7291946,
    "rewardFromCheckpoints": 90.47618,
    "rewardFromFinish": 0.0,
    "rewardFromTimeRunOut": 0.0,
    "rewardFromWall": -13.0,
    "rewardFromSpeed": -1.01999938,
    "rewardFromTime": -2.72698474,
    "rewardFromBrakes": 0.0
  },
  {
    "epNo": 2,
    "timesteps": 2872,
    "time": 57.41947,
    "wallHit": 0,
    "collidedWith": "",
    "distanceCovered": 425.22152709960938,
    "maxSpeed": 10.373139381408691,
    "avgSpeed": 7.4235684785182512,
    "totalReward": 141.385117,
    "rewardFromCheckpoints": 95.23808,
    "rewardFromFinish": 50.0,
    "rewardFromTimeRunOut": 0.0,
    "rewardFromWall": 0.0,
    "rewardFromSpeed": -0.979999363,
    "rewardFromTime": -2.87297416,
    "rewardFromBrakes": 0.0
  },
  {
    "epNo": 3,
    "timesteps": 2740,
    "time": 54.8041344,
    "wallHit": 1,
    "collidedWith": "Wall",
    "distanceCovered": 412.83926391601563,
    "maxSpeed": 10.338188171386719,
    "avgSpeed": 7.5517980269326346,
    "totalReward": 73.7652,
    "rewardFromCheckpoints": 90.47618,
    "rewardFromFinish": 0.0,
    "rewardFromTimeRunOut": 0.0,
    "rewardFromWall": -13.0,
    "rewardFromSpeed": -0.9699994,
    "rewardFromTime": -2.74098372,
    "rewardFromBrakes": 0.0
  },
  {
    "epNo": 4,
    "timesteps": 2710,
    "time": 54.1694374,
    "wallHit": 1,
    "collidedWith": "Wall",
    "distanceCovered": 407.982421875,
    "maxSpeed": 10.377961158752441,
    "avgSpeed": 7.5457787256454187,
    "totalReward": 73.7851944,
    "rewardFromCheckpoints": 90.47618,
    "rewardFromFinish": 0.0,
    "rewardFromTimeRunOut": 0.0,
    "rewardFromWall": -13.0,
    "rewardFromSpeed": -0.979999363,
    "rewardFromTime": -2.710986,
    "rewardFromBrakes": 0.0
  }
]