[
  {
    "epNo": 0,
    "timesteps": 0,
    "time": 0.0,
    "wallHit": 0,
    "collidedWith": "",
    "distanceCovered": 0.0,
    "maxSpeed": 0.0,
    "avgSpeed": 0.0,
    "totalReward": 0.0,
    "rewardFromCheckpoints": 0.0,
    "rewardFromFinish": 0.0,
    "rewardFromTimeRunOut": 0.0,
    "rewardFromWall": 0.0,
    "rewardFromSpeed": 0.0,
    "rewardFromTime": 0.0,
    "rewardFromBrakes": 0.0
  },
  {
    "epNo": 1,
    "timesteps": 2688,
    "time": 53.7324524,
    "wallHit": 0,
    "collidedWith": "",
    "distanceCovered": 401.15509033203125,
    "maxSpeed": 11.189034461975098,
    "avgSpeed": 7.483023610040421,
    "totalReward": 138.841019,
    "rewardFromCheckpoints": 93.75,
    "rewardFromFinish": 50.0,
    "rewardFromTimeRunOut": 0.0,
    "rewardFromWall": 0.0,
    "rewardFromSpeed": -2.21999836,
    "rewardFromTime": -2.68898749,
    "rewardFromBrakes": 0.0
  },
  {
    "epNo": 2,
    "timesteps": 2650,
    "time": 52.97449,
    "wallHit": 0,
    "collidedWith": "",
    "distanceCovered": 404.2822265625,
    "maxSpeed": 12.14824390411377,
    "avgSpeed": 7.6486218504916943,
    "totalReward": 140.069016,
    "rewardFromCheckpoints": 93.75,
    "rewardFromFinish": 50.0,
    "rewardFromTimeRunOut": 0.0,
    "rewardFromWall": 0.0,
    "rewardFromSpeed": -1.02999938,
    "rewardFromTime": -2.65099025,
    "rewardFromBrakes": 0.0
  },
  {
    "epNo": 3,
    "timesteps": 2521,
    "time": 50.4664879,
    "wallHit": 0,
    "collidedWith": "",
    "distanceCovered": 403.63629150390625,
    "maxSpeed": 11.497453689575195,
    "avgSpeed": 8.0268015579033438,
    "totalReward": 140.178,
    "rewardFromCheckpoints": 93.75,
    "rewardFromFinish": 50.0,
    "rewardFromTimeRunOut": 0.0,
    "rewardFromWall": 0.0,
    "rewardFromSpeed": -1.04999936,
    "rewardFromTime": -2.5219996,
    "rewardFromBrakes": 0.0
  }
]